odoo/addons/project_stage_last_update_date/README.rst
odoo/addons/project_stage_last_update_date/__init__.py
odoo/addons/project_stage_last_update_date/__manifest__.py
odoo/addons/project_stage_last_update_date/i18n/es.po
odoo/addons/project_stage_last_update_date/i18n/it.po
odoo/addons/project_stage_last_update_date/i18n/project_stage_last_update_date.pot
odoo/addons/project_stage_last_update_date/i18n/pt_BR.po
odoo/addons/project_stage_last_update_date/models/__init__.py
odoo/addons/project_stage_last_update_date/models/project_project.py
odoo/addons/project_stage_last_update_date/readme/CONTRIBUTORS.md
odoo/addons/project_stage_last_update_date/readme/DESCRIPTION.md
odoo/addons/project_stage_last_update_date/static/description/icon.png
odoo/addons/project_stage_last_update_date/static/description/index.html
odoo/addons/project_stage_last_update_date/tests/__init__.py
odoo/addons/project_stage_last_update_date/tests/test_project.py
odoo/addons/project_stage_last_update_date/views/project_project_views.xml
odoo_addon_project_stage_last_update_date-18.0.1.0.0.3.dist-info/METADATA
odoo_addon_project_stage_last_update_date-18.0.1.0.0.3.dist-info/WHEEL
odoo_addon_project_stage_last_update_date-18.0.1.0.0.3.dist-info/top_level.txt
odoo_addon_project_stage_last_update_date-18.0.1.0.0.3.dist-info/RECORD
